fal_ai_mcp_server/__init__.py
fal_ai_mcp_server/_version.py
fal_ai_mcp_server/main.py
fal_ai_mcp_server-0.1.2.dist-info/licenses/LICENSE
fal_ai_mcp_server-0.1.2.dist-info/METADATA
fal_ai_mcp_server-0.1.2.dist-info/WHEEL
fal_ai_mcp_server-0.1.2.dist-info/entry_points.txt
fal_ai_mcp_server-0.1.2.dist-info/top_level.txt
fal_ai_mcp_server-0.1.2.dist-info/RECORD
