Metadata-Version: 2.4
Name: fal-ai-mcp-server
Version: 0.1.2
Summary: An MCP (Model Contex Protocol) Server to use the fal.ai APIs to generate images and videos. 
Author-email: Piet Brömmel <piet.broemmel@gmail.com>
License-Expression: MIT
Project-URL: Homepage, https://github.com/piebro/fal-ai-mcp-server
Project-URL: Bug Tracker, https://github.com/piebro/fal-ai-mcp-server/issues
Keywords: mcp,server
Classifier: Development Status :: 4 - Beta
Classifier: Intended Audience :: Developers
Classifier: Programming Language :: Python :: 3
Classifier: Programming Language :: Python :: 3.10
Requires-Python: >=3.10
License-File: LICENSE
Requires-Dist: ruff
Requires-Dist: mcp
Requires-Dist: fal_client
Requires-Dist: requests
Dynamic: license-file
